project/setup.py
project/timings/__init__.py
project/timings/command_line.py
timings.egg-info/PKG-INFO
timings.egg-info/SOURCES.txt
timings.egg-info/dependency_links.txt
timings.egg-info/entry_points.txt
timings.egg-info/not-zip-safe
timings.egg-info/top_level.txt