Metadata-Version: 1.0
Name: timings
Version: 1.8
Summary: Convert time from seconds.
Home-page: UNKNOWN
Author: Himanshu Sharma
Author-email: UNKNOWN
License: MIT
Platform: UNKNOWN
